scratchml/__init__.py
scratchml/classification/KNN.py
scratchml/classification/LogisticRegression.py
scratchml/classification/SVM.py
scratchml/classification/__init__.py
scratchml/clustering/KMeans.py
scratchml/clustering/KMedoids.py
scratchml/clustering/__init__.py
scratchml/nn/Perceptron.py
scratchml/nn/__init__.py
scratchml/regression/MultipleLinearRegression.py
scratchml/regression/SimpleLinearRegression.py
scratchml/regression/__init__.py
scratchml/utils/ScratchMLExceptions.py
scratchml/utils/__init__.py
scratchml/utils/activation.py
scratchml/utils/distance.py
scratchml/utils/loss.py
tests/__init__.py
tests/context.py
tests/test_multiple_linear_regression.py
tests/test_simple_linear_regression.py
scratchml-0.4.dist-info/LICENSE
scratchml-0.4.dist-info/METADATA
scratchml-0.4.dist-info/WHEEL
scratchml-0.4.dist-info/top_level.txt
scratchml-0.4.dist-info/RECORD
